LICENSE.txt
MANIFEST.in
README.md
pyproject.toml
setup.cfg
setup.py
src/linkcheckmd/__init__.py
src/linkcheckmd/__main__.py
src/linkcheckmd/base.py
src/linkcheckmd/coro.py
src/linkcheckmd/files.py
src/linkcheckmd/sync.py
src/linkcheckmd.egg-info/PKG-INFO
src/linkcheckmd.egg-info/SOURCES.txt
src/linkcheckmd.egg-info/dependency_links.txt
src/linkcheckmd.egg-info/entry_points.txt
src/linkcheckmd.egg-info/requires.txt
src/linkcheckmd.egg-info/top_level.txt
src/linkcheckmd/tests/__init__.py
src/linkcheckmd/tests/badlink.md
src/linkcheckmd/tests/test_script.py