Metadata-Version: 2.1
Name: linkcheckmd
Version: 1.4.0
Summary: Check links for Markdown-based site
Home-page: https://github.com/scivision/linkchecker-markdown
Author: Michael Hirsch, Ph.D.
Author-email: scivision@users.noreply.github.com
License: UNKNOWN
Keywords: markdown,jekyll,hugo
Platform: UNKNOWN
Classifier: Development Status :: 5 - Production/Stable
Classifier: Environment :: Console
Classifier: Framework :: AsyncIO
Classifier: Intended Audience :: Developers
Classifier: Operating System :: OS Independent
Classifier: Programming Language :: Python :: 3
Classifier: Programming Language :: Python :: Implementation :: CPython
Classifier: Topic :: Internet :: WWW/HTTP :: Site Management :: Link Checking
Requires-Python: >=3.7
Provides-Extra: tests
Provides-Extra: lint
Provides-Extra: requests
